cmoss_package/__init__.py
cmossfuckerv1v2/__init__.py
my_package/__init__.py
cmoss_package-0.1.0.dist-info/METADATA
cmoss_package-0.1.0.dist-info/WHEEL
cmoss_package-0.1.0.dist-info/top_level.txt
cmoss_package-0.1.0.dist-info/RECORD
