Metadata-Version: 2.2
Name: cmoss-package
Version: 0.1.0
Summary: A simple package that adds two numbers
Home-page: https://github.com/yourusername/cmossfuckerv1v2
Author: cmoss
Author-email: cmoss <cmoss8227@gmail.com>
Requires-Python: >=3.11
Requires-Dist: build>=1.2.2
Requires-Dist: setuptools>=76.0.0
Dynamic: author
Dynamic: home-page
